celery_sentinel/__init__.py
celery_sentinel/celery.py
celery_sentinel/register.py
celery_sentinel/transport.py
celery_sentinel-0.0.1.dist-info/LICENSE
celery_sentinel-0.0.1.dist-info/METADATA
celery_sentinel-0.0.1.dist-info/WHEEL
celery_sentinel-0.0.1.dist-info/top_level.txt
celery_sentinel-0.0.1.dist-info/RECORD
