Metadata-Version: 2.1
Name: celery-sentinel
Version: 0.0.1
Summary: Redis-Sentinel transport for Celery
Home-page: https://github.com/kidig/celery-sentinel
Author: Dmitry Gerasimenko
License: MIT
Keywords: celery redis sentinel broker
Platform: UNKNOWN
Classifier: Intended Audience :: Developers
Classifier: Natural Language :: English
Classifier: License :: OSI Approved :: MIT License
Classifier: Programming Language :: Python
Classifier: Programming Language :: Python :: 3
Classifier: Programming Language :: Python :: 3.6
Classifier: Programming Language :: Python :: 3.7
Classifier: Programming Language :: Python :: 3.8
Classifier: Development Status :: 2 - Pre-Alpha
Requires-Dist: celery (==4.4.6)
Requires-Dist: setuptools
